LICENSE.txt
README.rst
setup.cfg
setup.py
grobid_quantities/__init__.py
grobid_quantities/client.py
grobid_quantities/quantities.py
grobid_quantities_client.egg-info/PKG-INFO
grobid_quantities_client.egg-info/SOURCES.txt
grobid_quantities_client.egg-info/dependency_links.txt
grobid_quantities_client.egg-info/not-zip-safe
grobid_quantities_client.egg-info/requires.txt
grobid_quantities_client.egg-info/top_level.txt