Metadata-Version: 2.1
Name: grobid-quantities-client
Version: 0.4.0
Summary: A minimal client for grobid-quantities service.
Home-page: https://github.com/lfoppiano/grobid-quantitites-python-client
Author: Luca Foppiano
Author-email: FOPPIANO.Luca@nims.go.jp
License: Apache 2.0
Keywords: measurements,text mining,tdm,grobid
Classifier: Development Status :: 4 - Beta
Classifier: Intended Audience :: Developers
Classifier: License :: OSI Approved :: Apache Software License
Classifier: Programming Language :: Python :: 3.6
License-File: LICENSE.txt
